ckanext/__init__.py
ckanext/core_fix/__init__.py
ckanext/core_fix/config.py
ckanext/core_fix/exceptions.py
ckanext/core_fix/helpers.py
ckanext/core_fix/plugin.py
ckanext/core_fix/utils.py
ckanext/core_fix/assets/webassets.yml
ckanext/core_fix/assets/css/button_icon_text_gap.css
ckanext/core_fix/assets/css/fontawesome_icons.css
ckanext/core_fix/assets/css/mobile_layout_breakpoint.css
ckanext/core_fix/assets/css/restyle_activity.css
ckanext/core_fix/assets/css/secondary_order.css
ckanext/core_fix/template_fix/dashboard_organization/user/dashboard_organization.html
ckanext/core_fix/template_fix/group_list_csrf/group/snippets/group_list.html
ckanext/core_fix/template_fix/markdown_macro/macros/form/markdown.html
ckanext/core_fix/template_fix/mobile_layout_breakpoint/page.html
ckanext/core_fix/template_fix/restyle_activity/snippets/stream.html
ckanext/core_fix/template_fix/restyle_activity/snippets/activities/activity_template.html
ckanext/core_fix/template_fix/restyle_activity/snippets/activities/changed_group.html
ckanext/core_fix/template_fix/restyle_activity/snippets/activities/changed_organization.html
ckanext/core_fix/template_fix/restyle_activity/snippets/activities/changed_package.html
ckanext/core_fix/template_fix/restyle_activity/snippets/activities/changed_user.html
ckanext/core_fix/template_fix/restyle_activity/snippets/activities/deleted_group.html
ckanext/core_fix/template_fix/restyle_activity/snippets/activities/deleted_organization.html
ckanext/core_fix/template_fix/restyle_activity/snippets/activities/deleted_package.html
ckanext/core_fix/template_fix/restyle_activity/snippets/activities/fallback.html
ckanext/core_fix/template_fix/restyle_activity/snippets/activities/follow_dataset.html
ckanext/core_fix/template_fix/restyle_activity/snippets/activities/follow_group.html
ckanext/core_fix/template_fix/restyle_activity/snippets/activities/follow_user.html
ckanext/core_fix/template_fix/restyle_activity/snippets/activities/new_group.html
ckanext_core_fix-0.7.1.dist-info/LICENSE
ckanext_core_fix-0.7.1.dist-info/METADATA
ckanext_core_fix-0.7.1.dist-info/WHEEL
ckanext_core_fix-0.7.1.dist-info/entry_points.txt
ckanext_core_fix-0.7.1.dist-info/top_level.txt
ckanext_core_fix-0.7.1.dist-info/RECORD
